{"/*":["X-Frame-Options: DENY","X-XSS-Protection: 1; mode=block","X-Content-Type-Options: nosniff","Referrer-Policy: same-origin"],"/styles.e32cdffe421b3ed793a1.css":["Cache-Control: public, max-age=31536000, immutable"],"/cb1608f2-c68468f648d6a1c8b4fc.js":["Cache-Control: public, max-age=31536000, immutable"],"/a9a7754c-9a69ecc4520dd749028f.js":["Cache-Control: public, max-age=31536000, immutable"],"/commons-f025b370b42714adb03c.js":["Cache-Control: public, max-age=31536000, immutable"],"/component---src-pages-404-js-ad765519c9749b223749.js":["Cache-Control: public, max-age=31536000, immutable"],"/component---src-pages-index-js-b0c96fb14d237010899c.js":["Cache-Control: public, max-age=31536000, immutable"],"/webpack-runtime-55727cde1deaacdef062.js":["Cache-Control: public, max-age=31536000, immutable"],"/framework-dec8e05adde60f55c9e1.js":["Cache-Control: public, max-age=31536000, immutable"],"/app-54a6178d61f20b2d67be.js":["Cache-Control: public, max-age=31536000, immutable"],"/static/*":["Cache-Control: public, max-age=31536000, immutable"],"/sw.js":["Cache-Control: public, max-age=0, must-revalidate"],"/404/":["Link: </webpack-runtime-55727cde1deaacdef062.js>; rel=preload; as=script; nopush","Link: </framework-dec8e05adde60f55c9e1.js>; rel=preload; as=script; nopush","Link: </app-54a6178d61f20b2d67be.js>; rel=preload; as=script; nopush","Link: </cb1608f2-c68468f648d6a1c8b4fc.js>; rel=preload; as=script; nopush","Link: </a9a7754c-9a69ecc4520dd749028f.js>; rel=preload; as=script; nopush","Link: </commons-f025b370b42714adb03c.js>; rel=preload; as=script; nopush","Link: </component---src-pages-404-js-ad765519c9749b223749.js>; rel=preload; as=script; nopush","Link: </page-data/app-data.json>; rel=preload; as=fetch; crossorigin; nopush","Link: </page-data/404/page-data.json>; rel=preload; as=fetch; crossorigin; nopush"],"/404.html":["Link: </webpack-runtime-55727cde1deaacdef062.js>; rel=preload; as=script; nopush","Link: </framework-dec8e05adde60f55c9e1.js>; rel=preload; as=script; nopush","Link: </app-54a6178d61f20b2d67be.js>; rel=preload; as=script; nopush","Link: </cb1608f2-c68468f648d6a1c8b4fc.js>; rel=preload; as=script; nopush","Link: </a9a7754c-9a69ecc4520dd749028f.js>; rel=preload; as=script; nopush","Link: </commons-f025b370b42714adb03c.js>; rel=preload; as=script; nopush","Link: </component---src-pages-404-js-ad765519c9749b223749.js>; rel=preload; as=script; nopush","Link: </page-data/app-data.json>; rel=preload; as=fetch; crossorigin; nopush","Link: </page-data/404.html/page-data.json>; rel=preload; as=fetch; crossorigin; nopush"],"/":["Link: </webpack-runtime-55727cde1deaacdef062.js>; rel=preload; as=script; nopush","Link: </framework-dec8e05adde60f55c9e1.js>; rel=preload; as=script; nopush","Link: </app-54a6178d61f20b2d67be.js>; rel=preload; as=script; nopush","Link: </cb1608f2-c68468f648d6a1c8b4fc.js>; rel=preload; as=script; nopush","Link: </a9a7754c-9a69ecc4520dd749028f.js>; rel=preload; as=script; nopush","Link: </commons-f025b370b42714adb03c.js>; rel=preload; as=script; nopush","Link: </component---src-pages-index-js-b0c96fb14d237010899c.js>; rel=preload; as=script; nopush","Link: </page-data/app-data.json>; rel=preload; as=fetch; crossorigin; nopush","Link: </page-data/index/page-data.json>; rel=preload; as=fetch; crossorigin; nopush"]}